{
  "mood_great": {
    "precision": 1.0,
    "recall": 1.0,
    "f1-score": 1.0,
    "support": 14,
    "confused_with": {}
  },
  "high_school_units": {
    "precision": 1.0,
    "recall": 1.0,
    "f1-score": 1.0,
    "support": 37,
    "confused_with": {}
  },
  "greet": {
    "precision": 1.0,
    "recall": 1.0,
    "f1-score": 1.0,
    "support": 13,
    "confused_with": {}
  },
  "cohort": {
    "precision": 1.0,
    "recall": 1.0,
    "f1-score": 1.0,
    "support": 50,
    "confused_with": {}
  },
  "deny": {
    "precision": 1.0,
    "recall": 1.0,
    "f1-score": 1.0,
    "support": 7,
    "confused_with": {}
  },
  "bot_challenge": {
    "precision": 1.0,
    "recall": 1.0,
    "f1-score": 1.0,
    "support": 4,
    "confused_with": {}
  },
  "enrollment": {
    "precision": 1.0,
    "recall": 1.0,
    "f1-score": 1.0,
    "support": 123,
    "confused_with": {}
  },
  "goodbye": {
    "precision": 1.0,
    "recall": 1.0,
    "f1-score": 1.0,
    "support": 10,
    "confused_with": {}
  },
  "mood_unhappy": {
    "precision": 1.0,
    "recall": 1.0,
    "f1-score": 1.0,
    "support": 14,
    "confused_with": {}
  },
  "affirm": {
    "precision": 1.0,
    "recall": 1.0,
    "f1-score": 1.0,
    "support": 7,
    "confused_with": {}
  },
  "accuracy": 1.0,
  "macro avg": {
    "precision": 1.0,
    "recall": 1.0,
    "f1-score": 1.0,
    "support": 279
  },
  "weighted avg": {
    "precision": 1.0,
    "recall": 1.0,
    "f1-score": 1.0,
    "support": 279
  },
  "micro avg": {
    "precision": 1.0,
    "recall": 1.0,
    "f1-score": 1.0,
    "support": 279
  }
}